tulip_api/__init__.py
tulip_api/cached_tulip_table.py
tulip_api/exceptions.py
tulip_api/py.typed
tulip_api/tulip_api.py
tulip_api/tulip_machine.py
tulip_api/tulip_table.py
tulip_api/tulip_table_csv_upload.py
tulip_api/tulip_table_link.py
tulip_api/asyncio/__init__.py
tulip_api/asyncio/py.typed
tulip_api/asyncio/tulip_api.py
tulip_api/asyncio/tulip_machine.py
tulip_api/asyncio/tulip_table.py
tulip_api/asyncio/tulip_table_csv_upload.py
community_tulip_api-0.1.9.dist-info/LICENSE
community_tulip_api-0.1.9.dist-info/METADATA
community_tulip_api-0.1.9.dist-info/WHEEL
community_tulip_api-0.1.9.dist-info/top_level.txt
community_tulip_api-0.1.9.dist-info/RECORD
