Metadata-Version: 2.1
Name: community-tulip-api
Version: 0.1.9
Summary: A community wrapper for the Tulip API
Home-page: https://github.com/henryivesjones/community-tulip-api
Author: Henry Jones
Author-email: Henry Jones <henryivesjones@tulip.co>
License: GNU GENERAL PUBLIC LICENSE
Project-URL: Homepage, https://github.com/henryivesjones/community-tulip-api
Project-URL: Bug Tracker, https://github.com/henryivesjones/community-tulip-api/issues
Keywords: tulip,api
Classifier: Programming Language :: Python :: 3
Classifier: Operating System :: OS Independent
Requires-Python: >=3.6
License-File: LICENSE
Requires-Dist: requests
Requires-Dist: python-dateutil
Requires-Dist: aiohttp
